MANIFEST.in
setup.py
anthill/blog/__init__.py
anthill/blog/admin.py
anthill/blog/handler.py
anthill/blog/options.py
anthill/blog/server.py
anthill/blog/model/__init__.py
anthill/blog/model/blog.py
anthill/blog/sql/blog_entries.sql
anthill/blog/sql/blogs.sql
anthill_blog.egg-info/PKG-INFO
anthill_blog.egg-info/SOURCES.txt
anthill_blog.egg-info/dependency_links.txt
anthill_blog.egg-info/namespace_packages.txt
anthill_blog.egg-info/not-zip-safe
anthill_blog.egg-info/requires.txt
anthill_blog.egg-info/top_level.txt