Metadata-Version: 1.0
Name: anthill-blog
Version: 0.2
Summary: A service to deliver news and patch notes feed to the users inside the game
Home-page: https://github.com/anthill-platform/anthill-blog
Author: desertkun
Author-email: desertkun@gmail.com
License: MIT
Platform: UNKNOWN
